README.md
setup.py
karvdash_client/__init__.py
karvdash_client/api.py
karvdash_client/cli.py
karvdash_client.egg-info/PKG-INFO
karvdash_client.egg-info/SOURCES.txt
karvdash_client.egg-info/dependency_links.txt
karvdash_client.egg-info/entry_points.txt
karvdash_client.egg-info/requires.txt
karvdash_client.egg-info/top_level.txt