Metadata-Version: 2.1
Name: karvdash-client
Version: 1.3.1
Summary: Client to the Karvdash (Kubernetes CARV Dashboard) API
Home-page: https://github.com/CARV-ICS-FORTH/karvdash
Author: FORTH-ICS
License: Apache-2.0
Platform: UNKNOWN
Classifier: Development Status :: 5 - Production/Stable
Classifier: Environment :: Console
Classifier: Programming Language :: Python :: 3.7
Classifier: Operating System :: OS Independent
Classifier: Topic :: Software Development :: Libraries :: Python Modules
Classifier: License :: OSI Approved :: Apache Software License
